MANIFEST.in
README.rst
setup.py
aliyunsdkvpc/__init__.py
aliyunsdkvpc/request/__init__.py
aliyunsdkvpc/request/v20160428/ActivateRouterInterfaceRequest.py
aliyunsdkvpc/request/v20160428/AddBandwidthPackageIpsRequest.py
aliyunsdkvpc/request/v20160428/AddBgpNetworkRequest.py
aliyunsdkvpc/request/v20160428/AddCommonBandwidthPackageIpRequest.py
aliyunsdkvpc/request/v20160428/AddGlobalAccelerationInstanceIpRequest.py
aliyunsdkvpc/request/v20160428/AllocateEipAddressRequest.py
aliyunsdkvpc/request/v20160428/AssociateEipAddressRequest.py
aliyunsdkvpc/request/v20160428/AssociateGlobalAccelerationInstanceRequest.py
aliyunsdkvpc/request/v20160428/AssociateHaVipRequest.py
aliyunsdkvpc/request/v20160428/AssociatePhysicalConnectionToVirtualBorderRouterRequest.py
aliyunsdkvpc/request/v20160428/CancelPhysicalConnectionRequest.py
aliyunsdkvpc/request/v20160428/ConnectRouterInterfaceRequest.py
aliyunsdkvpc/request/v20160428/CreateBandwidthPackageRequest.py
aliyunsdkvpc/request/v20160428/CreateBgpGroupRequest.py
aliyunsdkvpc/request/v20160428/CreateBgpPeerRequest.py
aliyunsdkvpc/request/v20160428/CreateCommonBandwidthPackageRequest.py
aliyunsdkvpc/request/v20160428/CreateCustomerGatewayRequest.py
aliyunsdkvpc/request/v20160428/CreateForwardEntryRequest.py
aliyunsdkvpc/request/v20160428/CreateGlobalAccelerationInstanceRequest.py
aliyunsdkvpc/request/v20160428/CreateHaVipRequest.py
aliyunsdkvpc/request/v20160428/CreateNatGatewayRequest.py
aliyunsdkvpc/request/v20160428/CreateNqaRequest.py
aliyunsdkvpc/request/v20160428/CreatePhysicalConnectionNewRequest.py
aliyunsdkvpc/request/v20160428/CreatePhysicalConnectionRequest.py
aliyunsdkvpc/request/v20160428/CreateRouteEntryRequest.py
aliyunsdkvpc/request/v20160428/CreateRouterInterfaceRequest.py
aliyunsdkvpc/request/v20160428/CreateSnatEntryRequest.py
aliyunsdkvpc/request/v20160428/CreateSslVpnClientCertRequest.py
aliyunsdkvpc/request/v20160428/CreateSslVpnServerRequest.py
aliyunsdkvpc/request/v20160428/CreateVSwitchRequest.py
dd_aliyun_python_sdk_vpc.egg-info/PKG-INFO
dd_aliyun_python_sdk_vpc.egg-info/SOURCES.txt
dd_aliyun_python_sdk_vpc.egg-info/dependency_links.txt
dd_aliyun_python_sdk_vpc.egg-info/requires.txt
dd_aliyun_python_sdk_vpc.egg-info/top_level.txt